{"date": "2019-09-03", "C": {"StackOverFlow": {"questions" : "309,372", "ranking" : "7"}, "Meetup": {"global" : {"meetups" : "226", "members" : "101,296", "ranking" : "12"}, "local" : {"meetups" : "12", "members" : "5,856", "ranking" : "9"}}, "TiobeIndex": {"currentPosition" : "2", "lastYearPosition" : "2"}, "Github": {"moreThen1000Stars" : "774", "projects" : "249,554", "ranking" : "7", "top10" : [{"name" : "linux", "stars" : "79,812", "url" : "https://github.com/torvalds/linux"}, {"name" : "netdata", "stars" : "40,738", "url" : "https://github.com/netdata/netdata"},{"name" : "redis", "stars" : "38,573", "url" : "https://github.com/antirez/redis"}, {"name" : "git", "stars" : "29,144", "url" : "https://github.com/git/git"}, {"name" : "php-src", "stars" : "24,705", "url" : "https://github.com/php/php-src"}, {"name" : "ijkplayer", "stars" : "24,422", "url" : "https://github.com/bilibili/ijkplayer"}, {"name" : "wrk", "stars" : "21,619", "url" : "https://github.com/wg/wrk"}, {"name" : "the_silver_searcher", "stars" : "18,636", "url" : "https://github.com/ggreer/the_silver_searcher"}, {"name" : "How-to-Make-a-Computer-Operating-System", "stars" : "18,228", "url" : "https://github.com/SamyPesse/How-to-Make-a-Computer-Operating-System"}, {"name" : "scrcpy", "stars" : "18,152", "url" : "https://github.com/Genymobile/scrcpy"}]}, "SpectrumRanking": {"currentPosition" : "4", "lastYearPosition" : "2"}}, "Cpp": {"StackOverFlow": {"questions" : "631,091", "ranking" : "6"}, "Meetup": {"global" : {"meetups" : "226", "members" : "101,296", "ranking" : "12"}, "local" : {"meetups" : "12", "members" : "5,856", "ranking" : "9"}}, "TiobeIndex": {"currentPosition" : "4", "lastYearPosition" : "3"}, "Github": {"moreThen1000Stars" : "929", "projects" : "319,456", "ranking" : "5", "top10" : [{"name" : "tensorflow", "stars" : "133,444", "url" : "https://github.com/tensorflow/tensorflow"}, {"name" : "electron", "stars" : "76,613", "url" : "https://github.com/electron/electron"}, {"name" : "terminal", "stars" : "51,417", "url" : "https://github.com/microsoft/terminal"}, {"name" : "swift", "stars" : "48,993", "url" : "https://github.com/apple/swift"}, {"name" : "bitcoin", "stars" : "39,918", "url" : "https://github.com/bitcoin/bitcoin"}, {"name" : "opencv", "stars" : "37,875", "url" : "https://github.com/opencv/opencv"},{"name" : "protobuf", "stars" : "36,942", "url" : "https://github.com/protocolbuffers/protobuf"}, {"name" : "nw.js", "stars" : "35,792", "url" : "https://github.com/nwjs/nw.js"}, {"name" : "x64dbg", "stars" : "34,218", "url" : "https://github.com/x64dbg/x64dbg"}, {"name" : "pytorch", "stars" : "31,304", "url" : "https://github.com/pytorch/pytorch"}]}, "SpectrumRanking": {"currentPosition" : "2", "lastYearPosition" : "4"}}, "Java": {"StackOverFlow": {"questions" : "1,582,761", "ranking" : "2"}, "Meetup": {"global" : {"meetups" : "2,230", "members" : "1,589,360", "ranking" : "3"}, "local" : {"meetups" : "88", "members" : "82,361", "ranking" : "2"}}, "TiobeIndex": {"currentPosition" : "1", "lastYearPosition" : "1"}, "Github": {"moreThen1000Stars" : "2,223", "projects" : "670,892", "ranking" : "3", "top10" : [{"name" : "JavaGuide", "stars" : "53,442", "url" : "https://github.com/Snailclimb/JavaGuide"}, {"name" : "java-design-patterns", "stars" : "50,980", "url" : "https://github.com/iluwatar/java-design-patterns"},{"name" : "elasticsearch", "stars" : "43,950", "url" : "https://github.com/elastic/elasticsearch"}, {"name" : "spring-boot", "stars" : "41,461", "url" : "https://github.com/spring-projects/spring-boot"}, {"name" : "RxJava", "stars" : "40,346", "url" : "https://github.com/ReactiveX/RxJava"},{"name" : "LeetCodeAnimation", "stars" : "40,032", "url" : "https://github.com/MisterBooo/LeetCodeAnimation"}, {"name" : "interviews", "stars" : "38,514", "url" : "https://github.com/kdn251/interviews"}, {"name" : "okhttp", "stars" : "34,148", "url" : "https://github.com/square/okhttp"}, {"name" : "retrofit", "stars" : "33,549", "url" : "https://github.com/square/retrofit"}, {"name" : "guava", "stars" : "33,526", "url" : "https://github.com/google/guava"}]}, "SpectrumRanking": {"currentPosition" : "3", "lastYearPosition" : "3"}}, "JavaScript": {"StackOverFlow": {"questions" : "1,864,251", "ranking" : "1"}, "Meetup": {"global" : {"meetups" : "5,828", "members" : "4,386,970", "ranking" : "1"}, "local" : {"meetups" : "139", "members" : "92,271", "ranking" : "1"}}, "TiobeIndex": {"currentPosition" : "7", "lastYearPosition" : "8"}, "Github": {"moreThen1000Stars" : "4,729", "projects" : "1,101,847", "ranking" : "1", "top10" : [{"name" : "freeCodeCamp", "stars" : "304,723", "url" : "https://github.com/freeCodeCamp/freeCodeCamp"},{"name" : "vue", "stars" : "147,356", "url" : "https://github.com/vuejs/vue"},{"name" : "bootstrap", "stars" : "135,648", "url" : "https://github.com/twbs/bootstrap"}, {"name" : "react", "stars" : "135,446", "url" : "https://github.com/facebook/react"}, {"name" : "javascript", "stars" : "88,550", "url" : "https://github.com/airbnb/javascript"}, {"name" : "d3", "stars" : "87,070", "url" : "https://github.com/d3/d3"}, {"name" : "react-native", "stars" : "80,606", "url" : "https://github.com/facebook/react-native"}, {"name" : "create-react-app", "stars" : "71,252", "url" : "https://github.com/facebook/create-react-app"},{"name" : "axios", "stars" : "64,243", "url" : "https://github.com/axios/axios"}, {"name" : "node", "stars" : "63,994", "url" : "https://github.com/nodejs/node"}]}, "SpectrumRanking": {"currentPosition" : "8", "lastYearPosition" : "7"}}, "Python": {"StackOverFlow": {"questions" : "1,238,338", "ranking" : "5"}, "Meetup": {"global" : {"meetups" : "2,460", "members" : "2,201,161", "ranking" : "2"}, "local" : {"meetups" : "44", "members" : "35,026", "ranking" : "3"}}, "TiobeIndex": {"currentPosition" : "3", "lastYearPosition" : "4"}, "Github": {"moreThen1000Stars" : "2,316", "projects" : "759,582", "ranking" : "2", "top10" : [{"name" : "awesome-python", "stars" : "72,558", "url" : "https://github.com/vinta/awesome-python"}, {"name" : "system-design-primer", "stars" : "72,272", "url" : "https://github.com/donnemartin/system-design-primer"}, {"name" : "public-apis", "stars" : "60,892", "url" : "https://github.com/public-apis/public-apis"}, {"name" : "models", "stars" : "57,174", "url" : "https://github.com/tensorflow/models"},{"name" : "youtube-dl", "stars" : "55,110", "url" : "https://github.com/ytdl-org/youtube-dl"},{"name" : "Python", "stars" : "54,470", "url" : "https://github.com/TheAlgorithms/Python"}, {"name" : "thefuck", "stars" : "46,531", "url" : "https://github.com/nvbn/thefuck"}, {"name" : "flask", "stars" : "46,231", "url" : "https://github.com/pallets/flask"}, {"name" : "keras", "stars" : "43,833", "url" : "https://github.com/keras-team/keras"}, {"name" : "django", "stars" : "43,824", "url" : "https://github.com/django/django"}]}, "SpectrumRanking": {"currentPosition" : "1", "lastYearPosition" : "1"}}, "Swift": {"StackOverFlow": {"questions" : "240,792", "ranking" : "9"}, "Meetup": {"global" : {"meetups" : "367", "members" : "201,343", "ranking" : "8"}, "local" : {"meetups" : "7", "members" : "2,313", "ranking" : "12"}}, "TiobeIndex": {"currentPosition" : "18", "lastYearPosition" : "11"}, "Github": {"moreThen1000Stars" : "648", "projects" : "83,538", "ranking" : "10", "top10" : [{"name" : "awesome-ios", "stars" : "32,796", "url" : "https://github.com/vsouza/awesome-ios"}, {"name" : "Alamofire", "stars" : "31,783", "url" : "https://github.com/Alamofire/Alamofire"}, {"name" : "ShadowsocksX-NG", "stars" : "23,052", "url" : "https://github.com/shadowsocks/ShadowsocksX-NG"}, {"name" : "Charts", "stars" : "21,538", "url" : "https://github.com/danielgindi/Charts"}, {"name" : "swift-algorithm-club", "stars" : "21,221", "url" : "https://github.com/raywenderlich/swift-algorithm-club"}, {"name" : "open-source-ios-apps", "stars" : "21,096", "url" : "https://github.com/dkhamsing/open-source-ios-apps"}, {"name" : "iina", "stars" : "20,427", "url" : "https://github.com/iina/iina"}, {"name" : "ReactiveCocoa", "stars" : "19,629", "url" : "https://github.com/ReactiveCocoa/ReactiveCocoa"}, {"name" : "SwiftyJSON", "stars" : "18,858", "url" : "https://github.com/SwiftyJSON/SwiftyJSON"}, {"name" : "open-source-mac-os-apps", "stars" : "18,171", "url" : "https://github.com/serhii-londar/open-source-mac-os-apps"}]}, "SpectrumRanking": {"currentPosition" : "18", "lastYearPosition" : "10"}}, "R": {"StackOverFlow": {"questions" : "304,502", "ranking" : "8"}, "Meetup": {"global" : {"meetups" : "230", "members" : "120,034", "ranking" : "10"}, "local" : {"meetups" : "5", "members" : "3,820", "ranking" : "11"}}, "TiobeIndex": {"currentPosition" : "20", "lastYearPosition" : "18"}, "Github": {"moreThen1000Stars" : "30", "projects" : "52,896", "ranking" : "11", "top10" : [{"name" : "ggplot2", "stars" : "3,975", "url" : "https://github.com/tidyverse/ggplot2"}, {"name" : "awesome-R", "stars" : "3,642", "url" : "https://github.com/qinwf/awesome-R"}, {"name" : "ML_for_Hackers", "stars" : "3,527", "url" : "https://github.com/johnmyleswhite/ML_for_Hackers"}, {"name" : "shiny", "stars" : "3,519", "url" : "https://github.com/rstudio/shiny"}, {"name" : "dplyr", "stars" : "3,035", "url" : "https://github.com/tidyverse/dplyr"}, {"name" : "AnomalyDetection", "stars" : "3,014", "url" : "https://github.com/twitter/AnomalyDetection"}, {"name" : "swirl_courses", "stars" : "3,005", "url" : "https://github.com/swirldev/swirl_courses"}, {"name" : "r4ds", "stars" : "2,047", "url" : "https://github.com/hadley/r4ds"}, {"name" : "devtools", "stars" : "1,837", "url" : "https://github.com/r-lib/devtools"}, {"name" : "knitr", "stars" : "1,823", "url" : "https://github.com/yihui/knitr"}]}, "SpectrumRanking": {"currentPosition" : "7", "lastYearPosition" : "6"}}, "Csharp": {"StackOverFlow": {"questions" : "1,340,316", "ranking" : "3"}, "Meetup": {"global" : {"meetups" : "873", "members" : "517,274", "ranking" : "6"}, "local" : {"meetups" : "36", "members" : "32,171", "ranking" : "4"}}, "TiobeIndex": {"currentPosition" : "5", "lastYearPosition" : "6"}, "Github": {"moreThen1000Stars" : "484", "projects" : "241,034", "ranking" : "8", "top10" : [{"name" : "shadowsocks-windows", "stars" : "42,081", "url" : "https://github.com/shadowsocks/shadowsocks-windows"}, {"name" : "CodeHub", "stars" : "21,373", "url" : "https://github.com/CodeHubApp/CodeHub"}, {"name" : "corefx", "stars" : "17,292", "url" : "https://github.com/dotnet/corefx"}, {"name" : "PowerShell", "stars" : "15,443", "url" : "https://github.com/PowerShell/PowerShell"}, {"name" : "Wox", "stars" : "14,281", "url" : "https://github.com/Wox-launcher/Wox"}, {"name" : "AspNetCore", "stars" : "13,527", "url" : "https://github.com/aspnet/AspNetCore"}, {"name" : "WaveFunctionCollapse", "stars" : "12,787", "url" : "https://github.com/mxgmn/WaveFunctionCollapse"}, {"name" : "coreclr", "stars" : "11,981", "url" : "https://github.com/dotnet/coreclr"}, {"name" : "roslyn", "stars" : "11,811", "url" : "https://github.com/dotnet/roslyn"}, {"name" : "dnSpy", "stars" : "11,518", "url" : "https://github.com/0xd4d/dnSpy"}]}, "SpectrumRanking": {"currentPosition" : "5", "lastYearPosition" : "5"}}, "Ruby": {"StackOverFlow": {"questions" : "207,079", "ranking" : "10"}, "Meetup": {"global" : {"meetups" : "852", "members" : "802,624", "ranking" : "5"}, "local" : {"meetups" : "17", "members" : "7,610", "ranking" : "7"}}, "TiobeIndex": {"currentPosition" : "11", "lastYearPosition" : "15"}, "Github": {"moreThen1000Stars" : "719", "projects" : "311,460", "ranking" : "6", "top10" : [{"name" : "rails", "stars" : "43,996", "url" : "https://github.com/rails/rails"}, {"name" : "jekyll", "stars" : "38,563", "url" : "https://github.com/jekyll/jekyll"}, {"name" : "discourse", "stars" : "28,985", "url" : "https://github.com/discourse/discourse"},{"name" : "fastlane", "stars" : "26,599", "url" : "https://github.com/fastlane/fastlane"}, {"name" : "awesome-awesomeness", "stars" : "24,754", "url" : "https://github.com/bayandin/awesome-awesomeness"}, {"name" : "huginn", "stars" : "22,076", "url" : "https://github.com/huginn/huginn"}, {"name" : "gitlabhq", "stars" : "21,982", "url" : "https://github.com/gitlabhq/gitlabhq"}, {"name" : "devdocs", "stars" : "21,294", "url" : "https://github.com/freeCodeCamp/devdocs"}, {"name" : "devise", "stars" : "20,155", "url" : "https://github.com/plataformatec/devise"}, {"name" : "vagrant", "stars" : "18,837", "url" : "https://github.com/hashicorp/vagrant"}]}, "SpectrumRanking": {"currentPosition" : "13", "lastYearPosition" : "12"}}, "PHP": {"StackOverFlow": {"questions" : "1,303,922", "ranking" : "4"}, "Meetup": {"global" : {"meetups" : "2,091", "members" : "1,151,346", "ranking" : "4"}, "local" : {"meetups" : "35", "members" : "20,747", "ranking" : "5"}}, "TiobeIndex": {"currentPosition" : "8", "lastYearPosition" : "7"}, "Github": {"moreThen1000Stars" : "860", "projects" : "379,779", "ranking" : "4", "top10" : [{"name" : "laravel", "stars" : "54,655", "url" : "https://github.com/laravel/laravel"}, {"name" : "jQuery-File-Upload", "stars" : "30,237", "url" : "https://github.com/blueimp/jQuery-File-Upload"}, {"name" : "Faker", "stars" : "21,708", "url" : "https://github.com/fzaninotto/Faker"}, {"name" : "symfony", "stars" : "21,546", "url" : "https://github.com/symfony/symfony"}, {"name" : "composer", "stars" : "20,807", "url" : "https://github.com/composer/composer"}, {"name" : "SecLists", "stars" : "19,868", "url" : "https://github.com/danielmiessler/SecLists"}, {"name" : "framework", "stars" : "18,626", "url" : "https://github.com/laravel/framework"}, {"name" : "DesignPatternsPHP", "stars" : "17,725", "url" : "https://github.com/domnikl/DesignPatternsPHP"}, {"name" : "CodeIgniter", "stars" : "17,584", "url" : "https://github.com/bcit-ci/CodeIgniter"}, {"name" : "guzzle", "stars" : "17,547", "url" : "https://github.com/guzzle/guzzle"}]}, "SpectrumRanking": {"currentPosition" : "6", "lastYearPosition" : "8"}}, "Kotlin": {"StackOverFlow": {"questions" : "27,504", "ranking" : "13"}, "Meetup": {"global" : {"meetups" : "244", "members" : "109,348", "ranking" : "11"}, "local" : {"meetups" : "6", "members" : "4,238", "ranking" : "10"}}, "TiobeIndex": {"currentPosition" : "45", "lastYearPosition" : "N/A"}, "Github": {"moreThen1000Stars" : "151", "projects" : "33,793", "ranking" : "14", "top10" : [{"name" : "android-architecture", "stars" : "33,964", "url" : "https://github.com/googlesamples/android-architecture"}, {"name" : "kotlin", "stars" : "28,919", "url" : "https://github.com/JetBrains/kotlin"}, {"name" : "shadowsocks-android", "stars" : "25,949", "url" : "https://github.com/shadowsocks/shadowsocks-android"}, {"name" : "leakcanary", "stars" : "23,512", "url" : "https://github.com/square/leakcanary"}, {"name" : "iosched", "stars" : "18,989", "url" : "https://github.com/google/iosched"},{"name" : "profile-summary-for-github", "stars" : "18,868", "url" : "https://github.com/tipsy/profile-summary-for-github"},{"name" : "p3c", "stars" : "17,976", "url" : "https://github.com/alibaba/p3c"}, {"name" : "material-dialogs", "stars" : "16,428", "url" : "https://github.com/afollestad/material-dialogs"}, {"name" : "anko", "stars" : "14,976", "url" : "https://github.com/Kotlin/anko"}, {"name" : "flexbox-layout", "stars" : "14,470", "url" : "https://github.com/google/flexbox-layout"}]}, "SpectrumRanking": {"currentPosition" : "N/A", "lastYearPosition" : "N/A"}}, "Scala": {"StackOverFlow": {"questions" : "91,726", "ranking" : "11"}, "Meetup": {"global" : {"meetups" : "633", "members" : "450,887", "ranking" : "7"}, "local" : {"meetups" : "25", "members" : "17,967", "ranking" : "6"}}, "TiobeIndex": {"currentPosition" : "36", "lastYearPosition" : "N/A"}, "Github": {"moreThen1000Stars" : "117", "projects" : "39,305", "ranking" : "12", "top10" : [{"name" : "spark", "stars" : "23,234", "url" : "https://github.com/apache/spark"}, {"name" : "prisma", "stars" : "15,513", "url" : "https://github.com/prisma/prisma"}, {"name" : "scala", "stars" : "12,051", "url" : "https://github.com/scala/scala"}, {"name" : "predictionio", "stars" : "12,049", "url" : "https://github.com/apache/predictionio"}, {"name" : "playframework", "stars" : "11,302", "url" : "https://github.com/playframework/playframework"}, {"name" : "akka", "stars" : "10,269", "url" : "https://github.com/akka/akka"}, {"name" : "kafka-manager", "stars" : "7,875", "url" : "https://github.com/yahoo/kafka-manager"}, {"name" : "gitbucket", "stars" : "7,799", "url" : "https://github.com/gitbucket/gitbucket"}, {"name" : "finagle", "stars" : "7,259", "url" : "https://github.com/twitter/finagle"}, {"name" : "source-han-sans", "stars" : "6,970", "url" : "https://github.com/adobe-fonts/source-han-sans"}]}, "SpectrumRanking": {"currentPosition" : "12", "lastYearPosition" : "14"}}, "Go": {"StackOverFlow": {"questions" : "40,281", "ranking" : "12"}, "Meetup": {"global" : {"meetups" : "327", "members" : "170,792", "ranking" : "9"}, "local" : {"meetups" : "10", "members" : "6,738", "ranking" : "8"}}, "TiobeIndex": {"currentPosition" : "17", "lastYearPosition" : "17"}, "Github": {"moreThen1000Stars" : "1,220", "projects" : "143,563", "ranking" : "9", "top10" : [{"name" : "go", "stars" : "62,962", "url" : "https://github.com/golang/go"}, {"name" : "kubernetes", "stars" : "57,401", "url" : "https://github.com/kubernetes/kubernetes"}, {"name" : "moby", "stars" : "54,800", "url" : "https://github.com/moby/moby"}, {"name" : "awesome-go", "stars" : "47,477", "url" : "https://github.com/avelino/awesome-go"}, {"name" : "lantern", "stars" : "44,610", "url" : "https://github.com/getlantern/lantern"}, {"name" : "hugo", "stars" : "37,843", "url" : "https://github.com/gohugoio/hugo"}, {"name" : "build-web-application-with-golang", "stars" : "31,963", "url" : "https://github.com/astaxie/build-web-application-with-golang"}, {"name" : "gogs", "stars" : "31,543", "url" : "https://github.com/gogs/gogs"}, {"name" : "gin", "stars" : "30,902", "url" : "https://github.com/gin-gonic/gin"}, {"name" : "syncthing", "stars" : "27,599", "url" : "https://github.com/syncthing/syncthing"}]}, "SpectrumRanking": {"currentPosition" : "9", "lastYearPosition" : "9"}}, "Groovy": {"StackOverFlow": {"questions" : "23,739", "ranking" : "14"}, "Meetup": {"global" : {"meetups" : "55", "members" : "28,243", "ranking" : "14"}, "local" : {"meetups" : "2", "members" : "626", "ranking" : "14"}}, "TiobeIndex": {"currentPosition" : "13", "lastYearPosition" : "44"}, "Github": {"moreThen1000Stars" : "13", "projects" : "12,364", "ranking" : "15", "top10" : [{"name" : "gradle", "stars" : "9,522", "url" : "https://github.com/gradle/gradle"}, {"name" : "rundeck", "stars" : "3,306", "url" : "https://github.com/rundeck/rundeck"}, {"name" : "pipeline-examples", "stars" : "2,977", "url" : "https://github.com/jenkinsci/pipeline-examples"}, {"name" : "asgard", "stars" : "2,206", "url" : "https://github.com/Netflix/asgard"}, {"name" : "gradle_plugin_android_aspectjx", "stars" : "2,073", "url" : "https://github.com/HujiangTechnology/gradle_plugin_android_aspectjx"}, {"name" : "gradle-versions-plugin", "stars" : "2,003", "url" : "https://github.com/ben-manes/gradle-versions-plugin"}, {"name" : "shadow", "stars" : "1,662", "url" : "https://github.com/johnrengelman/shadow"}, {"name" : "bintray-release", "stars" : "1,545", "url" : "https://github.com/novoda/bintray-release"}, {"name" : "sdk-manager-plugin", "stars" : "1,436", "url" : "https://github.com/JakeWharton/sdk-manager-plugin"}, {"name" : "SmartThingsPublic", "stars" : "1,350", "url" : "https://github.com/SmartThingsCommunity/SmartThingsPublic"}]}, "SpectrumRanking": {"currentPosition" : "N/A", "lastYearPosition" : "N/A"}}, "Rust": {"StackOverFlow": {"questions" : "13,251", "ranking" : "15"}, "Meetup": {"global" : {"meetups" : "191", "members" : "64,173", "ranking" : "13"}, "local" : {"meetups" : "4", "members" : "639", "ranking" : "13"}}, "TiobeIndex": {"currentPosition" : "28", "lastYearPosition" : "N/A"}, "Github": {"moreThen1000Stars" : "200", "projects" : "34,649", "ranking" : "13", "top10" : [{"name" : "996.ICU", "stars" : "247,198", "url" : "https://github.com/996icu/996.ICU"}, {"name" : "rust", "stars" : "38,866", "url" : "https://github.com/rust-lang/rust"}, {"name" : "deno", "stars" : "37,873", "url" : "https://github.com/denoland/deno"}, {"name" : "alacritty", "stars" : "18,077", "url" : "https://github.com/jwilm/alacritty"}, {"name" : "xi-editor", "stars" : "16,648", "url" : "https://github.com/xi-editor/xi-editor"}, {"name" : "ripgrep", "stars" : "16,056", "url" : "https://github.com/BurntSushi/ripgrep"}, {"name" : "bat", "stars" : "15,060", "url" : "https://github.com/sharkdp/bat"}, {"name" : "servo", "stars" : "14,743", "url" : "https://github.com/servo/servo"}, {"name" : "libra", "stars" : "12,168", "url" : "https://github.com/libra/libra"}, {"name" : "awesome-rust", "stars" : "12,135", "url" : "https://github.com/rust-unofficial/awesome-rust"}]}, "SpectrumRanking": {"currentPosition" : "28", "lastYearPosition" : "22"}}}